jsslib/__init__.py
jsslib/__version__.py
jsslib/base.lex
jsslib/jsslib.py
jsslib/jsslib_arm64.dll
jsslib/jsslib_x64.dll
jsslib/libjsslib.dylib
jsslib/libjsslib.so
jsslib/test.py
jsslib-1.0.21.dist-info/licenses/LICENSE
jsslib-1.0.21.dist-info/METADATA
jsslib-1.0.21.dist-info/WHEEL
jsslib-1.0.21.dist-info/top_level.txt
jsslib-1.0.21.dist-info/RECORD
